[
  {
    "name": "E1M6",
    "parent": "Central Processing (E1M6)",
    "children": [
      {
        "name": "E1M6 Entrance",
        "chest_unopened_img": "/images/items/levelstart.png",
        "chest_opened_img": "/images/items/levelstart.png",
        "access_rules": ["$access|null"],
        "sections": [
          {
            "ref": "Central Processing (E1M6)/E1M6 Entrance",
            "name": "Level Start",
            "item_count": 1
          }
        ],
        "map_locations": [
          {
            "map": "e1m6",
            "restrict_visibility_rules": ["ep1_on"],
            "size": 20,
            "x": 370,
            "y": 640
          }
        ]
      },
      {
        "name": "End of Eastern Corridor",
        "access_rules": [
          "@Central Processing (E1M6)/End of Eastern Corridor"
        ],
        "sections": [
          {
            "ref": "Central Processing (E1M6)/End of Eastern Corridor",
            "name": "Items",
            "item_count": 2
          }
        ],
        "map_locations": [
          {
            "map": "e1m6",
            "restrict_visibility_rules": ["ep1_on"],
            "x": 590,
            "y": 655
          }
        ]
      },
      {
        "name": "Shotgun",
        "access_rules": ["@Central Processing (E1M6)/Shotgun"],
        "sections": [
          {
            "ref": "Central Processing (E1M6)/Shotgun",
            "name": "Item",
            "item_count": 1
          }
        ],
        "map_locations": [
          {
            "map": "e1m6",
            "restrict_visibility_rules": ["ep1_on"],
            "x": 296,
            "y": 625
          }
        ]
      },
      {
        "name": "Pre-Blue Key Door Equipment Closet",
        "access_rules": [
          "@Central Processing (E1M6)/Pre-Blue Key Door Equipment Closet"
        ],
        "sections": [
          {
            "ref": "Central Processing (E1M6)/Pre-Blue Key Door Equipment Closet",
            "name": "Items",
            "item_count": 3
          }
        ],
        "map_locations": [
          {
            "map": "e1m6",
            "restrict_visibility_rules": ["ep1_on"],
            "x": 522,
            "y": 557
          }
        ]
      },
      {
        "name": "Armor",
        "access_rules": ["@Central Processing (E1M6)/Armor"],
        "sections": [
          {
            "ref": "Central Processing (E1M6)/Armor",
            "name": "Item",
            "item_count": 1
          }
        ],
        "map_locations": [
          {
            "map": "e1m6",
            "restrict_visibility_rules": ["ep1_on"],
            "x": 386,
            "y": 428
          }
        ]
      },
      {
        "name": "Armor 4",
        "access_rules": ["@Central Processing (E1M6)/Armor 4"],
        "sections": [
          {
            "ref": "Central Processing (E1M6)/Armor 4",
            "name": "Item",
            "item_count": 1
          }
        ],
        "map_locations": [
          {
            "map": "e1m6",
            "restrict_visibility_rules": ["ep1_on"],
            "x": 250,
            "y": 470
          }
        ]
      },
      {
        "name": "Supercharge 2",
        "access_rules": ["@Central Processing (E1M6)/Supercharge 2"],
        "sections": [
          {
            "ref": "Central Processing (E1M6)/Supercharge 2",
            "name": "Item",
            "item_count": 1
          }
        ],
        "map_locations": [
          {
            "map": "e1m6",
            "restrict_visibility_rules": ["ep1_on"],
            "x": 424,
            "y": 128
          }
        ]
      },
      {
        "name": "Post-Blue Key Door Equipment Closet",
        "access_rules": [
          "@Central Processing (E1M6)/Post-Blue Key Door Equipment Closet"
        ],
        "sections": [
          {
            "ref": "Central Processing (E1M6)/Post-Blue Key Door Equipment Closet",
            "name": "Items",
            "item_count": 3
          }
        ],
        "map_locations": [
          {
            "map": "e1m6",
            "restrict_visibility_rules": ["ep1_on"],
            "x": 557,
            "y": 506
          }
        ]
      },
      {
        "name": "Computer Area Map",
        "access_rules": ["@Central Processing (E1M6)/Computer Area Map"],
        "sections": [
          {
            "ref": "Central Processing (E1M6)/Computer Area Map",
            "name": "Item",
            "item_count": 1
          }
        ],
        "map_locations": [
          {
            "map": "e1m6",
            "restrict_visibility_rules": ["ep1_on"],
            "x": 935,
            "y": 654
          }
        ]
      },
      {
        "name": "Backpack 3",
        "access_rules": ["@Central Processing (E1M6)/Backpack 3"],
        "sections": [
          {
            "ref": "Central Processing (E1M6)/Backpack 3",
            "name": "Item",
            "item_count": 1
          }
        ],
        "map_locations": [
          {
            "map": "e1m6",
            "restrict_visibility_rules": ["ep1_on"],
            "x": 478,
            "y": 180
          }
        ]
      },
      {
        "name": "Armor 3",
        "access_rules": ["@Central Processing (E1M6)/Armor 3"],
        "sections": [
          {
            "ref": "Central Processing (E1M6)/Armor 3",
            "name": "Item",
            "item_count": 1
          }
        ],
        "map_locations": [
          {
            "map": "e1m6",
            "restrict_visibility_rules": ["$difficulty_range|1|high"],
            "x": 230,
            "y": 200
          }
        ]
      },
      {
        "name": "Supercharge",
        "access_rules": ["@Central Processing (E1M6)/Supercharge"],
        "sections": [
          {
            "ref": "Central Processing (E1M6)/Supercharge",
            "name": "Item",
            "item_count": 1
          }
        ],
        "map_locations": [
          {
            "map": "e1m6",
            "restrict_visibility_rules": ["ep1_on"],
            "x": 46,
            "y": 788
          }
        ]
      },
      {
        "name": "Blue Keycard",
        "access_rules": ["@Central Processing (E1M6)/Blue Keycard"],
        "sections": [
          {
            "ref": "Central Processing (E1M6)/Blue Keycard",
            "name": "Item",
            "item_count": 1
          }
        ],
        "map_locations": [
          {
            "map": "e1m6",
            "restrict_visibility_rules": ["ep1_on"],
            "x": 131,
            "y": 686
          }
        ]
      },
      {
        "name": "Partial Invisibility 2",
        "access_rules": [
          "@Central Processing (E1M6)/Partial Invisibility 2"
        ],
        "sections": [
          {
            "ref": "Central Processing (E1M6)/Partial Invisibility 2",
            "name": "Item",
            "item_count": 1
          }
        ],
        "map_locations": [
          {
            "map": "e1m6",
            "restrict_visibility_rules": ["ep1_on"],
            "x": 337,
            "y": 654
          }
        ]
      },
      {
        "name": "Mega Armor",
        "access_rules": ["@Central Processing (E1M6)/Mega Armor"],
        "sections": [
          {
            "ref": "Central Processing (E1M6)/Mega Armor",
            "name": "Item",
            "item_count": 1
          }
        ],
        "map_locations": [
          {
            "map": "e1m6",
            "restrict_visibility_rules": ["ep1_on"],
            "x": 195,
            "y": 685
          }
        ]
      },
      {
        "name": "E1M6 Exit",
        "access_rules": ["@Central Processing (E1M6)/E1M6 Exit"],
        "sections": [
          {
            "ref": "Central Processing (E1M6)/E1M6 Exit",
            "name": "Level Completed",
            "hosted_item": "e1m6_complete"
          }
        ],
        "map_locations": [
          {
            "map": "e1m6",
            "restrict_visibility_rules": ["ep1_on"],
            "size": 20,
            "x": 75,
            "y": 83
          }
        ]
      }
    ]
  }
]
