[
  {
    "name": "MAP24",
    "parent": "The Chasm (MAP24)",
    "children": [
      {
        "name": "MAP24 Entrance",
        "chest_unopened_img": "/images/items/levelstart.png",
        "chest_opened_img": "/images/items/levelstart.png",
        "access_rules": ["$access|null"],
        "sections": [
          {
            "ref": "The Chasm (MAP24)/MAP24 Entrance",
            "name": "Level Start",
            "item_count": 1
          }
        ],
        "map_locations": [
          {
            "map": "map24",
            "restrict_visibility_rules": ["ep3_on"],
            "size": 20,
            "x": 0,
            "y": 0
          }
        ]
      },
      {
        "name": "Shotgun",
        "access_rules": ["@The Chasm (MAP24)/Shotgun"],
        "sections": [
          {
            "ref": "The Chasm (MAP24)/Shotgun",
            "name": "Item",
            "item_count": 1
          }
        ],
        "map_locations": [
          {
            "map": "map24",
            "restrict_visibility_rules": ["ep3_on"],
            "x": 24,
            "y": 0
          }
        ]
      },
      {
        "name": "Super Shotgun",
        "access_rules": ["@The Chasm (MAP24)/Super Shotgun"],
        "sections": [
          {
            "ref": "The Chasm (MAP24)/Super Shotgun",
            "name": "Item",
            "item_count": 1
          }
        ],
        "map_locations": [
          {
            "map": "map24",
            "restrict_visibility_rules": ["ep3_on"],
            "x": 48,
            "y": 0
          }
        ]
      },
      {
        "name": "Rocket Launcher",
        "access_rules": ["@The Chasm (MAP24)/Rocket Launcher"],
        "sections": [
          {
            "ref": "The Chasm (MAP24)/Rocket Launcher",
            "name": "Item",
            "item_count": 1
          }
        ],
        "map_locations": [
          {
            "map": "map24",
            "restrict_visibility_rules": ["ep3_on"],
            "x": 72,
            "y": 0
          }
        ]
      },
      {
        "name": "Plasma Gun",
        "access_rules": ["@The Chasm (MAP24)/Plasma Gun"],
        "sections": [
          {
            "ref": "The Chasm (MAP24)/Plasma Gun",
            "name": "Item",
            "item_count": 1
          }
        ],
        "map_locations": [
          {
            "map": "map24",
            "restrict_visibility_rules": ["ep3_on"],
            "x": 96,
            "y": 0
          }
        ]
      },
      {
        "name": "BFG9000",
        "access_rules": ["@The Chasm (MAP24)/BFG9000"],
        "sections": [
          {
            "ref": "The Chasm (MAP24)/BFG9000",
            "name": "Item",
            "item_count": 1
          }
        ],
        "map_locations": [
          {
            "map": "map24",
            "restrict_visibility_rules": ["ep3_on"],
            "x": 120,
            "y": 0
          }
        ]
      },
      {
        "name": "Armor",
        "access_rules": ["@The Chasm (MAP24)/Armor"],
        "sections": [
          {
            "ref": "The Chasm (MAP24)/Armor",
            "name": "Item",
            "item_count": 1
          }
        ],
        "map_locations": [
          {
            "map": "map24",
            "restrict_visibility_rules": ["ep3_on"],
            "x": 144,
            "y": 0
          }
        ]
      },
      {
        "name": "Megasphere",
        "access_rules": ["@The Chasm (MAP24)/Megasphere"],
        "sections": [
          {
            "ref": "The Chasm (MAP24)/Megasphere",
            "name": "Item",
            "item_count": 1
          }
        ],
        "map_locations": [
          {
            "map": "map24",
            "restrict_visibility_rules": ["ep3_on"],
            "x": 168,
            "y": 0
          }
        ]
      },
      {
        "name": "Megasphere 2",
        "access_rules": ["@The Chasm (MAP24)/Megasphere 2"],
        "sections": [
          {
            "ref": "The Chasm (MAP24)/Megasphere 2",
            "name": "Item",
            "item_count": 1
          }
        ],
        "map_locations": [
          {
            "map": "map24",
            "restrict_visibility_rules": ["ep3_on"],
            "x": 192,
            "y": 0
          }
        ]
      },
      {
        "name": "Backpack",
        "access_rules": ["@The Chasm (MAP24)/Backpack"],
        "sections": [
          {
            "ref": "The Chasm (MAP24)/Backpack",
            "name": "Item",
            "item_count": 1
          }
        ],
        "map_locations": [
          {
            "map": "map24",
            "restrict_visibility_rules": ["ep3_on"],
            "x": 216,
            "y": 0
          }
        ]
      },
      {
        "name": "Berserk",
        "access_rules": ["@The Chasm (MAP24)/Berserk"],
        "sections": [
          {
            "ref": "The Chasm (MAP24)/Berserk",
            "name": "Item",
            "item_count": 1
          }
        ],
        "map_locations": [
          {
            "map": "map24",
            "restrict_visibility_rules": ["ep3_on"],
            "x": 240,
            "y": 0
          }
        ]
      },
      {
        "name": "Berserk 2",
        "access_rules": ["@The Chasm (MAP24)/Berserk 2"],
        "sections": [
          {
            "ref": "The Chasm (MAP24)/Berserk 2",
            "name": "Item",
            "item_count": 1
          }
        ],
        "map_locations": [
          {
            "map": "map24",
            "restrict_visibility_rules": ["ep3_on"],
            "x": 264,
            "y": 0
          }
        ]
      },
      {
        "name": "Invulnerability",
        "access_rules": ["@The Chasm (MAP24)/Invulnerability"],
        "sections": [
          {
            "ref": "The Chasm (MAP24)/Invulnerability",
            "name": "Item",
            "item_count": 1
          }
        ],
        "map_locations": [
          {
            "map": "map24",
            "restrict_visibility_rules": ["ep3_on"],
            "x": 288,
            "y": 0
          }
        ]
      },
      {
        "name": "Blue Keycard",
        "access_rules": ["@The Chasm (MAP24)/Blue Keycard"],
        "sections": [
          {
            "ref": "The Chasm (MAP24)/Blue Keycard",
            "name": "Item",
            "item_count": 1
          }
        ],
        "map_locations": [
          {
            "map": "map24",
            "restrict_visibility_rules": ["ep3_on"],
            "x": 312,
            "y": 0
          }
        ]
      },
      {
        "name": "Red Keycard",
        "access_rules": ["@The Chasm (MAP24)/Red Keycard"],
        "sections": [
          {
            "ref": "The Chasm (MAP24)/Red Keycard",
            "name": "Item",
            "item_count": 1
          }
        ],
        "map_locations": [
          {
            "map": "map24",
            "restrict_visibility_rules": ["ep3_on"],
            "x": 336,
            "y": 0
          }
        ]
      },
      {
        "name": "MAP24 Exit",
        "access_rules": ["@The Chasm (MAP24)/MAP24 Exit"],
        "sections": [
          {
            "ref": "The Chasm (MAP24)/MAP24 Exit",
            "name": "Level Completed",
            "hosted_item": "e3m4_complete"
          }
        ],
        "map_locations": [
          {
            "map": "map24",
            "restrict_visibility_rules": ["ep3_on"],
            "size": 20,
            "x": 360,
            "y": 0
          }
        ]
      }
    ]
  }
]
