[
  {
    "name": "MAP31",
    "parent": "Wolfenstein (MAP31)",
    "children": [
      {
        "name": "MAP31 Entrance",
        "chest_unopened_img": "/images/items/levelstart.png",
        "chest_opened_img": "/images/items/levelstart.png",
        "access_rules": ["$access|null"],
        "sections": [
          {
            "ref": "Wolfenstein (MAP31)/MAP31 Entrance",
            "name": "Level Start",
            "item_count": 1
          }
        ],
        "map_locations": [
          {
            "map": "map31",
            "restrict_visibility_rules": ["ep4_on"],
            "size": 20,
            "x": 0,
            "y": 0
          }
        ]
      },
      {
        "name": "Shotgun",
        "access_rules": ["@Wolfenstein (MAP31)/Shotgun"],
        "sections": [
          {
            "ref": "Wolfenstein (MAP31)/Shotgun",
            "name": "Item",
            "item_count": 1
          }
        ],
        "map_locations": [
          {
            "map": "map31",
            "restrict_visibility_rules": ["ep4_on"],
            "x": 24,
            "y": 0
          }
        ]
      },
      {
        "name": "Super Shotgun",
        "access_rules": ["@Wolfenstein (MAP31)/Super Shotgun"],
        "sections": [
          {
            "ref": "Wolfenstein (MAP31)/Super Shotgun",
            "name": "Item",
            "item_count": 1
          }
        ],
        "map_locations": [
          {
            "map": "map31",
            "restrict_visibility_rules": ["ep4_on"],
            "x": 48,
            "y": 0
          }
        ]
      },
      {
        "name": "Chaingun",
        "access_rules": ["@Wolfenstein (MAP31)/Chaingun"],
        "sections": [
          {
            "ref": "Wolfenstein (MAP31)/Chaingun",
            "name": "Item",
            "item_count": 1
          }
        ],
        "map_locations": [
          {
            "map": "map31",
            "restrict_visibility_rules": ["ep4_on"],
            "x": 72,
            "y": 0
          }
        ]
      },
      {
        "name": "Rocket Launcher",
        "access_rules": ["@Wolfenstein (MAP31)/Rocket Launcher"],
        "sections": [
          {
            "ref": "Wolfenstein (MAP31)/Rocket Launcher",
            "name": "Item",
            "item_count": 1
          }
        ],
        "map_locations": [
          {
            "map": "map31",
            "restrict_visibility_rules": ["ep4_on"],
            "x": 96,
            "y": 0
          }
        ]
      },
      {
        "name": "Plasma Gun",
        "access_rules": ["@Wolfenstein (MAP31)/Plasma Gun"],
        "sections": [
          {
            "ref": "Wolfenstein (MAP31)/Plasma Gun",
            "name": "Item",
            "item_count": 1
          }
        ],
        "map_locations": [
          {
            "map": "map31",
            "restrict_visibility_rules": ["ep4_on"],
            "x": 120,
            "y": 0
          }
        ]
      },
      {
        "name": "BFG9000",
        "access_rules": ["@Wolfenstein (MAP31)/BFG9000"],
        "sections": [
          {
            "ref": "Wolfenstein (MAP31)/BFG9000",
            "name": "Item",
            "item_count": 1
          }
        ],
        "map_locations": [
          {
            "map": "map31",
            "restrict_visibility_rules": ["ep4_on"],
            "x": 144,
            "y": 0
          }
        ]
      },
      {
        "name": "Supercharge",
        "access_rules": ["@Wolfenstein (MAP31)/Supercharge"],
        "sections": [
          {
            "ref": "Wolfenstein (MAP31)/Supercharge",
            "name": "Item",
            "item_count": 1
          }
        ],
        "map_locations": [
          {
            "map": "map31",
            "restrict_visibility_rules": ["ep4_on"],
            "x": 168,
            "y": 0
          }
        ]
      },
      {
        "name": "Megasphere",
        "access_rules": ["@Wolfenstein (MAP31)/Megasphere"],
        "sections": [
          {
            "ref": "Wolfenstein (MAP31)/Megasphere",
            "name": "Item",
            "item_count": 1
          }
        ],
        "map_locations": [
          {
            "map": "map31",
            "restrict_visibility_rules": ["ep4_on"],
            "x": 192,
            "y": 0
          }
        ]
      },
      {
        "name": "Backpack",
        "access_rules": ["@Wolfenstein (MAP31)/Backpack"],
        "sections": [
          {
            "ref": "Wolfenstein (MAP31)/Backpack",
            "name": "Item",
            "item_count": 1
          }
        ],
        "map_locations": [
          {
            "map": "map31",
            "restrict_visibility_rules": ["ep4_on"],
            "x": 216,
            "y": 0
          }
        ]
      },
      {
        "name": "Backpack 2",
        "access_rules": ["@Wolfenstein (MAP31)/Backpack 2"],
        "sections": [
          {
            "ref": "Wolfenstein (MAP31)/Backpack 2",
            "name": "Item",
            "item_count": 1
          }
        ],
        "map_locations": [
          {
            "map": "map31",
            "restrict_visibility_rules": ["ep4_on"],
            "x": 240,
            "y": 0
          }
        ]
      },
      {
        "name": "Backpack 3",
        "access_rules": ["@Wolfenstein (MAP31)/Backpack 3"],
        "sections": [
          {
            "ref": "Wolfenstein (MAP31)/Backpack 3",
            "name": "Item",
            "item_count": 1
          }
        ],
        "map_locations": [
          {
            "map": "map31",
            "restrict_visibility_rules": ["ep4_on"],
            "x": 264,
            "y": 0
          }
        ]
      },
      {
        "name": "Backpack 4",
        "access_rules": ["@Wolfenstein (MAP31)/Backpack 4"],
        "sections": [
          {
            "ref": "Wolfenstein (MAP31)/Backpack 4",
            "name": "Item",
            "item_count": 1
          }
        ],
        "map_locations": [
          {
            "map": "map31",
            "restrict_visibility_rules": ["ep4_on"],
            "x": 288,
            "y": 0
          }
        ]
      },
      {
        "name": "Berserk",
        "access_rules": ["@Wolfenstein (MAP31)/Berserk"],
        "sections": [
          {
            "ref": "Wolfenstein (MAP31)/Berserk",
            "name": "Item",
            "item_count": 1
          }
        ],
        "map_locations": [
          {
            "map": "map31",
            "restrict_visibility_rules": ["ep4_on"],
            "x": 312,
            "y": 0
          }
        ]
      },
      {
        "name": "Invisibility",
        "access_rules": ["@Wolfenstein (MAP31)/Invisibility"],
        "sections": [
          {
            "ref": "Wolfenstein (MAP31)/Invisibility",
            "name": "Item",
            "item_count": 1
          }
        ],
        "map_locations": [
          {
            "map": "map31",
            "restrict_visibility_rules": ["ep4_on"],
            "x": 336,
            "y": 0
          }
        ]
      },
      {
        "name": "MAP31 Exit",
        "access_rules": ["@Wolfenstein (MAP31)/MAP31 Exit"],
        "sections": [
          {
            "ref": "Wolfenstein (MAP31)/MAP31 Exit",
            "name": "Level Completed",
            "hosted_item": "e4m1_complete"
          }
        ],
        "map_locations": [
          {
            "map": "map31",
            "restrict_visibility_rules": ["ep4_on"],
            "size": 20,
            "x": 360,
            "y": 0
          }
        ]
      }
    ]
  }
]
