[
  {
    "name": "E3M3",
    "parent": "Pandemonium (E3M3)",
    "children": [
      {
        "name": "E3M3 Entrance",
        "chest_unopened_img": "/images/items/levelstart.png",
        "chest_opened_img": "/images/items/levelstart.png",
        "access_rules": ["$access|null"],
        "sections": [
          {
            "ref": "Pandemonium (E3M3)/E3M3 Entrance",
            "name": "Level Start",
            "item_count": 1
          }
        ],
        "map_locations": [
          {
            "map": "e3m3",
            "restrict_visibility_rules": ["ep3_on"],
            "size": 20,
            "x": 396,
            "y": 775
          }
        ]
      },
      {
        "name": "Berserk",
        "access_rules": ["@Pandemonium (E3M3)/Berserk"],
        "sections": [
          {
            "ref": "Pandemonium (E3M3)/Berserk",
            "name": "Item",
            "item_count": 1
          }
        ],
        "map_locations": [
          {
            "map": "e3m3",
            "restrict_visibility_rules": ["ep3_on"],
            "x": 812,
            "y": 260
          }
        ]
      },
      {
        "name": "Chaingun",
        "access_rules": ["@Pandemonium (E3M3)/Chaingun"],
        "sections": [
          {
            "ref": "Pandemonium (E3M3)/Chaingun",
            "name": "Item",
            "item_count": 1
          }
        ],
        "map_locations": [
          {
            "map": "e3m3",
            "restrict_visibility_rules": ["ep3_on"],
            "x": 552,
            "y": 335
          }
        ]
      },
      {
        "name": "BFG9000",
        "access_rules": ["@Pandemonium (E3M3)/BFG9000"],
        "sections": [
          {
            "ref": "Pandemonium (E3M3)/BFG9000",
            "name": "Item",
            "item_count": 1
          }
        ],
        "map_locations": [
          {
            "map": "e3m3",
            "restrict_visibility_rules": ["ep3_on"],
            "x": 378,
            "y": 398
          }
        ]
      },
      {
        "name": "Supercharge",
        "access_rules": ["@Pandemonium (E3M3)/Supercharge"],
        "sections": [
          {
            "ref": "Pandemonium (E3M3)/Supercharge",
            "name": "Item",
            "item_count": 1
          }
        ],
        "map_locations": [
          {
            "map": "e3m3",
            "restrict_visibility_rules": ["ep3_on"],
            "x": 318,
            "y": 308
          }
        ]
      },
      {
        "name": "Invulnerability",
        "access_rules": ["@Pandemonium (E3M3)/Invulnerability"],
        "sections": [
          {
            "ref": "Pandemonium (E3M3)/Invulnerability",
            "name": "Item",
            "item_count": 1
          }
        ],
        "map_locations": [
          {
            "map": "e3m3",
            "restrict_visibility_rules": ["ep3_on"],
            "x": 206,
            "y": 390
          }
        ]
      },
      {
        "name": "Blue Skull Key",
        "access_rules": ["@Pandemonium (E3M3)/Blue Skull Key"],
        "sections": [
          {
            "ref": "Pandemonium (E3M3)/Blue Skull Key",
            "name": "Item",
            "item_count": 1
          }
        ],
        "map_locations": [
          {
            "map": "e3m3",
            "restrict_visibility_rules": ["ep3_on"],
            "x": 420,
            "y": 645
          }
        ]
      },
      {
        "name": "Mega Armor",
        "access_rules": ["@Pandemonium (E3M3)/Mega Armor"],
        "sections": [
          {
            "ref": "Pandemonium (E3M3)/Mega Armor",
            "name": "Item",
            "item_count": 1
          }
        ],
        "map_locations": [
          {
            "map": "e3m3",
            "restrict_visibility_rules": ["ep3_on"],
            "x": 447,
            "y": 522
          }
        ]
      },
      {
        "name": "Shotgun",
        "note": "May not be present on Med/UV/NM",
        "access_rules": ["@Pandemonium (E3M3)/Shotgun"],
        "sections": [
          {
            "ref": "Pandemonium (E3M3)/Shotgun",
            "name": "Item",
            "item_count": 1
          }
        ],
        "map_locations": [
          {
            "map": "e3m3",
            "restrict_visibility_rules": ["ep3_on"],
            "x": 346,
            "y": 522
          }
        ]
      },
      {
        "name": "Armor",
        "access_rules": ["@Pandemonium (E3M3)/Armor"],
        "sections": [
          {
            "ref": "Pandemonium (E3M3)/Armor",
            "name": "Item",
            "item_count": 1
          }
        ],
        "map_locations": [
          {
            "map": "e3m3",
            "restrict_visibility_rules": ["ep3_on"],
            "x": 705,
            "y": 110
          }
        ]
      },
      {
        "name": "Backpack",
        "access_rules": ["@Pandemonium (E3M3)/Backpack"],
        "sections": [
          {
            "ref": "Pandemonium (E3M3)/Backpack",
            "name": "Item",
            "item_count": 1
          }
        ],
        "map_locations": [
          {
            "map": "e3m3",
            "restrict_visibility_rules": ["ep3_on"],
            "x": 705,
            "y": 140
          }
        ]
      },
      {
        "name": "Computer Area Map",
        "access_rules": ["@Pandemonium (E3M3)/Computer Area Map"],
        "sections": [
          {
            "ref": "Pandemonium (E3M3)/Computer Area Map",
            "name": "Item",
            "item_count": 1
          }
        ],
        "map_locations": [
          {
            "map": "e3m3",
            "restrict_visibility_rules": ["ep3_on"],
            "x": 355,
            "y": 212
          }
        ]
      },
      {
        "name": "Mega Armor 2",
        "access_rules": ["@Pandemonium (E3M3)/Mega Armor 2"],
        "sections": [
          {
            "ref": "Pandemonium (E3M3)/Mega Armor 2",
            "name": "Item",
            "item_count": 1
          }
        ],
        "map_locations": [
          {
            "map": "e3m3",
            "restrict_visibility_rules": ["ep3_on"],
            "x": 270,
            "y": 220
          }
        ]
      },
      {
        "name": "Shotgun 2",
        "note": "May not be present on Med/UV/NM",
        "access_rules": ["@Pandemonium (E3M3)/Shotgun 2"],
        "sections": [
          {
            "ref": "Pandemonium (E3M3)/Shotgun 2",
            "name": "Item",
            "item_count": 1
          }
        ],
        "map_locations": [
          {
            "map": "e3m3",
            "restrict_visibility_rules": ["ep3_on"],
            "x": 362,
            "y": 765
          }
        ]
      },
      {
        "name": "Shotgun 3",
        "note": "May not be present on Med/UV/NM",
        "access_rules": ["@Pandemonium (E3M3)/Shotgun 3"],
        "sections": [
          {
            "ref": "Pandemonium (E3M3)/Shotgun 3",
            "name": "Item",
            "item_count": 1
          }
        ],
        "map_locations": [
          {
            "map": "e3m3",
            "restrict_visibility_rules": ["ep3_on"],
            "x": 0,
            "y": 0
          }
        ]
      },
      {
        "name": "Rocket Launcher",
        "access_rules": ["@Pandemonium (E3M3)/Rocket Launcher"],
        "sections": [
          {
            "ref": "Pandemonium (E3M3)/Rocket Launcher",
            "name": "Item",
            "item_count": 1
          }
        ],
        "map_locations": [
          {
            "map": "e3m3",
            "restrict_visibility_rules": ["ep3_on"],
            "x": 734,
            "y": 140
          }
        ]
      },
      {
        "name": "E3M3 Exit",
        "access_rules": ["@Pandemonium (E3M3)/E3M3 Exit"],
        "sections": [
          {
            "ref": "Pandemonium (E3M3)/E3M3 Exit",
            "name": "Level Completed",
            "hosted_item": "e3m3_complete"
          }
        ],
        "map_locations": [
          {
            "map": "e3m3",
            "restrict_visibility_rules": ["ep3_on"],
            "size": 20,
            "x": 525,
            "y": 15
          }
        ]
      }
    ]
  }
]
