[
  {
    "name": "E2M5",
    "parent": "Command Center (E2M5)",
    "children": [
      {
        "name": "E2M5 Entrance",
        "chest_unopened_img": "/images/items/levelstart.png",
        "chest_opened_img": "/images/items/levelstart.png",
        "access_rules": [
          "$access|null"
        ],
        "sections": [
          {
            "ref": "Command Center (E2M5)/E2M5 Entrance",
            "name": "Level Start",
            "item_count": 1
          }
        ],
        "map_locations": [
          {
            "map": "e2m5",
            "restrict_visibility:rules": [
              "ep2_on"
            ],
            "size": 20,
            "x": 480,
            "y": 36
          }
        ]
      },
      {
        "name": "Backpack",
        "access_rules": [
          "@Command Center (E2M5)/Backpack"
        ],
        "sections": [
          {
            "ref": "Command Center (E2M5)/Backpack",
            "name": "Item",
            "item_count": 1
          }
        ],
        "map_locations": [
          {
            "map": "e2m5",
            "restrict_visibility:rules": [
              "ep2_on"
            ],
            "x": 500,
            "y": 287
          }
        ]
      },
      {
        "name": "Mega Armor",
        "access_rules": [
          "@Command Center (E2M5)/Mega Armor"
        ],
        "sections": [
          {
            "ref": "Command Center (E2M5)/Mega Armor",
            "name": "Item",
            "item_count": 1
          }
        ],
        "map_locations": [
          {
            "map": "e2m5",
            "restrict_visibility:rules": [
              "ep2_on"
            ],
            "x": 800,
            "y": 315
          }
        ]
      },
      {
        "name": "Berserk",
        "access_rules": [
          "@Command Center (E2M5)/Berserk"
        ],
        "sections": [
          {
            "ref": "Command Center (E2M5)/Berserk",
            "name": "Item",
            "item_count": 1
          }
        ],
        "map_locations": [
          {
            "map": "e2m5",
            "restrict_visibility:rules": [
              "ep2_on"
            ],
            "x": 460,
            "y": 287
          }
        ]
      },
      {
        "name": "Chaingun",
        "access_rules": [
          "@Command Center (E2M5)/Chaingun"
        ],
        "sections": [
          {
            "ref": "Command Center (E2M5)/Chaingun",
            "name": "Item",
            "item_count": 1
          }
        ],
        "map_locations": [
          {
            "map": "e2m5",
            "restrict_visibility:rules": [
              "ep2_on"
            ],
            "x": 453,
            "y": 434
          }
        ]
      },
      {
        "name": "Chainsaw",
        "access_rules": [
          "@Command Center (E2M5)/Chainsaw"
        ],
        "sections": [
          {
            "ref": "Command Center (E2M5)/Chainsaw",
            "name": "Item",
            "item_count": 1
          }
        ],
        "map_locations": [
          {
            "map": "e2m5",
            "restrict_visibility:rules": [
              "ep2_on"
            ],
            "x": 585,
            "y": 506
          }
        ]
      },
      {
        "name": "Plasma Gun",
        "access_rules": [
          "@Command Center (E2M5)/Plasma Gun"
        ],
        "sections": [
          {
            "ref": "Command Center (E2M5)/Plasma Gun",
            "name": "Item",
            "item_count": 1
          }
        ],
        "map_locations": [
          {
            "map": "e2m5",
            "restrict_visibility:rules": [
              "ep2_on"
            ],
            "x": 235,
            "y": 109
          }
        ]
      },
      {
        "name": "Computer Area Map",
        "access_rules": [
          "@Command Center (E2M5)/Computer Area Map"
        ],
        "sections": [
          {
            "ref": "Command Center (E2M5)/Computer Area Map",
            "name": "Item",
            "item_count": 1
          }
        ],
        "map_locations": [
          {
            "map": "e2m5",
            "restrict_visibility:rules": [
              "ep2_on"
            ],
            "x": 506,
            "y": 434
          }
        ]
      },
      {
        "name": "Armor",
        "access_rules": [
          "@Command Center (E2M5)/Armor"
        ],
        "sections": [
          {
            "ref": "Command Center (E2M5)/Armor",
            "name": "Item",
            "item_count": 1
          }
        ],
        "map_locations": [
          {
            "map": "e2m5",
            "restrict_visibility:rules": [
              "ep2_on"
            ],
            "x": 650,
            "y": 280
          }
        ]
      },
      {
        "name": "Armor 2",
        "access_rules": [
          "@Command Center (E2M5)/Armor 2"
        ],
        "sections": [
          {
            "ref": "Command Center (E2M5)/Armor 2",
            "name": "Item",
            "item_count": 1
          }
        ],
        "map_locations": [
          {
            "map": "e2m5",
            "restrict_visibility:rules": [
              "ep2_on"
            ],
            "x": 300,
            "y": 633
          }
        ]
      },
      {
        "name": "Partial Invisibility",
        "access_rules": [
          "@Command Center (E2M5)/Partial Invisibility"
        ],
        "sections": [
          {
            "ref": "Command Center (E2M5)/Partial Invisibility",
            "name": "Item",
            "item_count": 1
          }
        ],
        "map_locations": [
          {
            "map": "e2m5",
            "restrict_visibility:rules": [
              "ep2_on"
            ],
            "x": 389,
            "y": 704
          }
        ]
      },
      {
        "name": "E2M5 Exit",
        "access_rules": [
          "@Command Center (E2M5)/E2M5 Exit"
        ],
        "sections": [
          {
            "ref": "Command Center (E2M5)/E2M5 Exit",
            "name": "Level Completed",
            "hosted_item": "e2m5_complete"
          }
        ],
        "map_locations": [
          {
            "map": "e2m5",
            "restrict_visibility:rules": [
              "ep2_on"
            ],
            "size": 20,
            "x": 770,
            "y": 175
          }
        ]
      },
      {
        "name": "E2M5 Secret Exit",
        "access_rules": [
          "@Command Center (E2M5)/E2M5 Secret Exit"
        ],
        "sections": [
          {
            "ref": "Command Center (E2M5)/E2M5 Secret Exit",
            "name": "Level Completed",
            "hosted_item": "e2m5_complete"
          }
        ],
        "map_locations": [
          {
            "map": "e2m5",
            "restrict_visibility:rules": [
              "ep2_on"
            ],
            "size": 20,
            "x": 731,
            "y": 49
          }
        ]
      }
    ]
  }
]